{
  "project_info": {
    "project_number": "1030993996989",
    "project_id": "futureeducation2024",
    "storage_bucket": "futureeducation2024.appspot.com"
  },
  "client": [
    {
      "client_info": {
        "mobilesdk_app_id": "1:1030993996989:android:11568091b44e7a35d49bd4",
        "android_client_info": {
          "package_name": "com.example.future_education_analysis"
        }
      },
      "oauth_client": [],
      "api_key": [
        {
          "current_key": "AIzaSyD8iAsKwbcrq0CsNyRyLDsmLV0MYuI5VX8"
        }
      ],
      "services": {
        "appinvite_service": {
          "other_platform_oauth_client": []
        }
      }
    }
  ],
  "configuration_version": "1"
}